jade/__init__.py
jade/__main__.py
jade/builder.py
jade/config.py
jade/page.py
jade/path.py
jade/commands/__init__.py
jade/commands/initialise/__init__.py
jade/commands/initialise/files.py
jade/commands/initialise/initialise.py
jade_md-0.0.4.dist-info/METADATA
jade_md-0.0.4.dist-info/WHEEL
jade_md-0.0.4.dist-info/top_level.txt
jade_md-0.0.4.dist-info/RECORD
