Metadata-Version: 2.1
Name: jade-md
Version: 0.0.4
Summary: Jade - A Python library for rendering markdown to HTML for Flask.
Home-page: https://github.com/sam-kenney/jade
Author: Sam Kenney
Author-email: sam.kenney@me.com
License: MIT
Requires-Dist: flask (==2.2.2)
Requires-Dist: jinja2 (==3.1.2)
Requires-Dist: markdown (==3.4.1)
Requires-Dist: pyyaml (==6.0)
